Metadata-Version: 1.1
Name: LayoutEditor
Version: 20180418
Summary: Python wrapper for the LayoutEditor/LayoutScript
Home-page: https://layouteditor.com
Author: juspertor GmbH
Author-email: python@juspertor.com
License: UNKNOWN
Keywords: EDA gds gdsII OASIS layout
Platform: UNKNOWN
Classifier: Development Status :: 5 - Production/Stable
Classifier: Intended Audience :: Science/Research
Classifier: Topic :: Scientific/Engineering :: Electronic Design Automation (EDA) 
Classifier: License :: OSI Approved :: MIT License 
Classifier: Programming Language :: Python :: 2
Classifier: Programming Language :: Python :: 2.7
Classifier: Programming Language :: Python :: 3
Classifier: Programming Language :: Python :: 3.4
Classifier: Programming Language :: Python :: 3.5
Classifier: Programming Language :: Python :: 3.6
